aew/__init__.py
aew-0.0.6.dist-info/LICENSE.md
aew-0.0.6.dist-info/METADATA
aew-0.0.6.dist-info/WHEEL
aew-0.0.6.dist-info/top_level.txt
aew-0.0.6.dist-info/RECORD
