Metadata-Version: 2.1
Name: aew
Version: 0.0.6
Summary: An unofficial basic parser for blog posts on https://allelitewrestling.com.
Author-email: csm10495 <csm10495@gmail.com>
License: MIT License
Project-URL: homepage, http://github.com/csm10495/aew
Project-URL: repository, http://github.com/csm10495/aew
Project-URL: documentation, https://csm10495.github.io/aew
Classifier: Intended Audience :: Developers
Classifier: Natural Language :: English
Classifier: Operating System :: POSIX
Classifier: Operating System :: Microsoft :: Windows
Classifier: Programming Language :: Python
Classifier: Programming Language :: Python :: 3
Requires-Python: >=3.9
License-File: LICENSE.md
Requires-Dist: requests >=2.27
Requires-Dist: beautifulsoup4
Requires-Dist: python-dateutil
